IR2Vec-2.1.1.dist-info/WHEEL
IR2Vec-2.1.1.dist-info/top_level.txt
IR2Vec-2.1.1.dist-info/RECORD
IR2Vec-2.1.1.dist-info/METADATA
ir2vec/__init__.py
ir2vec/preparation.py
ir2vec/seedEmbeddingVocab.txt
ir2vec/core.cpp
IR2Vec/core.cpython-38-x86_64-linux-gnu.so
